top/__init__.py
top/__main__.py
Karanvir_101903698-0.0.9.dist-info/LICENSE
Karanvir_101903698-0.0.9.dist-info/METADATA
Karanvir_101903698-0.0.9.dist-info/WHEEL
Karanvir_101903698-0.0.9.dist-info/entry_points.txt
Karanvir_101903698-0.0.9.dist-info/top_level.txt
Karanvir_101903698-0.0.9.dist-info/RECORD
