Metadata-Version: 2.1
Name: Karanvir-101903698
Version: 0.0.9
Summary: Topsis Package
Home-page: UNKNOWN
Author: Karanvir Singh
Author-email: <ksingh5_be19@thapar.edu>
License: UNKNOWN
Keywords: python,topsis,thapar
Platform: UNKNOWN
Classifier: Development Status :: 3 - Alpha
Classifier: Intended Audience :: Developers
Classifier: Topic :: Software Development :: Build Tools
Classifier: License :: OSI Approved :: MIT License
Classifier: Programming Language :: Python :: 3
Classifier: Programming Language :: Python :: 3.8
Classifier: Programming Language :: Python :: 3.9
License-File: LICENSE
Requires-Dist: numpy
Requires-Dist: pandas
